{
  "step": "step3_5",
  "keyword": "eラーニング 企業",
  "emotional_analysis": {
    "primary_emotion": "導入失敗への不安（損失回避）",
    "secondary_emotions": [
      "業務過多による疲弊感（現状からの脱却願望）",
      "経営層と現場の板挟みによる孤独感",
      "正しい選択をして評価されたいという承認欲求"
    ],
    "pain_points": [
      "高額なシステムを導入しても、結局社員が使わず『デジタル廃墟』化してしまうことへの恐怖",
      "「DX推進」と丸投げされたが、IT専門知識に自信がなく、ベンダーの専門用語に圧倒されている",
      "Excelでの受講管理や会場手配など、付加価値の低い事務作業に忙殺され、本来の人材育成業務に手が回らない"
    ],
    "desires": [
      "「システムを入れた」だけでなく、「社員が自発的に学び始めた」という成果を経営層に報告したい",
      "煩雑な事務作業から解放され、定時で帰れるような効率的な運用体制を作りたい",
      "何かあった時にすぐに相談できる、システムベンダー以上の「パートナー」が欲しい"
    ]
  },
  "human_touch_patterns": [
    {
      "type": "experience",
      "content": "「研修の前日は、会場設営と資料印刷で残業が確定する」「終わった後は、未提出者の督促メールとExcelへの転記作業が待っている」という、泥臭い現場のリアルな描写。",
      "placement_suggestion": "記事冒頭（リード文）で読者の現状を代弁し、「私のことが書かれている」と思わせる"
    },
    {
      "type": "emotion",
      "content": "「機能表の『○』の数だけで選んで、本当に大丈夫だろうか？」という、スペック比較だけでは拭えない漠然とした不安を言語化する。",
      "placement_suggestion": "比較表の直前または直後（決定回避の法則への対策）"
    },
    {
      "type": "empathy",
      "content": "「eラーニングの導入は、ゴールではなく『孤独な戦い』の始まりになりがちです。だからこそ、並走してくれるサポート体制が命綱になります。」と、担当者のプレッシャーを肯定し、寄り添う。",
      "placement_suggestion": "サポート体制や定着支援機能の解説セクション"
    }
  ],
  "experience_episodes": [
    {
      "scenario": "Excel管理の限界とヒヤリハット",
      "narrative": "「受講状況を管理するExcelファイル、誰かがフィルタをかけたまま保存してしまい、集計がズレていたことに会議直前で気づいた冷や汗…。もう、手作業での管理は限界だと感じた瞬間でした。」",
      "lesson": "LMS導入は「楽をするため」ではなく、「正確で安全なデータ管理」のために必須の投資である（自分への言い訳・正当化）。"
    },
    {
      "scenario": "過去の失敗（または他社の失敗談）",
      "narrative": "「『多機能で安いから』と決めた以前のツール。マニュアルを見ないとどこに何があるかわからない複雑な画面で、結局社員からの『使い方がわからない』という問い合わせ対応に追われ、半年で誰もログインしなくなりました。」",
      "lesson": "機能の豊富さよりも、マニュアルなしで直感的に使える「UI/UX（使いやすさ）」こそが、定着の最大の鍵である。"
    }
  ],
  "emotional_hooks": [
    "「ジムの会員になっても行かなければ意味がないように、eラーニングも『ログインされなければ』ただのコストです。」",
    "「研修担当者を『雑務係』から『組織を変える戦略家』へ。eラーニング導入は、あなたのキャリアを変える転機になります。」",
    "「上司を説得するための『費用対効果』の算出、一人で悩んでいませんか？稟議書の書き方までサポートする視点で選びましょう。」"
  ],
  "phase_emotional_map": {
    "phase1": {
      "dominant_emotion": "",
      "empathy_statements": [],
      "experience_episodes": []
    },
    "phase2": {
      "dominant_emotion": "",
      "empathy_statements": [],
      "experience_episodes": []
    },
    "phase3": {
      "dominant_emotion": "",
      "empathy_statements": [],
      "experience_episodes": []
    }
  },
  "behavioral_economics_hooks": {
    "loss_aversion_hook": "",
    "social_proof_hook": "",
    "authority_hook": "",
    "scarcity_hook": ""
  },
  "placement_instructions": [],
  "raw_output": "指定されたペルソナ（30代後半〜40代の人事・総務マネージャー）と分析データに基づき、記事に人間味と共感を加えるための要素をJSON形式で生成しました。\n\n競合が「機能の羅列」に終始しているのに対し、**「導入後の孤独な運用」や「定着しない恐怖」という担当者の本音（インサイト）**に寄り添う構成案です。\n\n```json\n{\n  \"emotional_analysis\": {\n    \"primary_emotion\": \"導入失敗への不安（損失回避）\",\n    \"secondary_emotions\": [\n      \"業務過多による疲弊感（現状からの脱却願望）\",\n      \"経営層と現場の板挟みによる孤独感\",\n      \"正しい選択をして評価されたいという承認欲求\"\n    ],\n    \"pain_points\": [\n      \"高額なシステムを導入しても、結局社員が使わず『デジタル廃墟』化してしまうことへの恐怖\",\n      \"「DX推進」と丸投げされたが、IT専門知識に自信がなく、ベンダーの専門用語に圧倒されている\",\n      \"Excelでの受講管理や会場手配など、付加価値の低い事務作業に忙殺され、本来の人材育成業務に手が回らない\"\n    ],\n    \"desires\": [\n      \"「システムを入れた」だけでなく、「社員が自発的に学び始めた」という成果を経営層に報告したい\",\n      \"煩雑な事務作業から解放され、定時で帰れるような効率的な運用体制を作りたい\",\n      \"何かあった時にすぐに相談できる、システムベンダー以上の「パートナー」が欲しい\"\n    ]\n  },\n  \"human_touch_patterns\": [\n    {\n      \"type\": \"experience\",\n      \"content\": \"「研修の前日は、会場設営と資料印刷で残業が確定する」「終わった後は、未提出者の督促メールとExcelへの転記作業が待っている」という、泥臭い現場のリアルな描写。\",\n      \"placement_suggestion\": \"記事冒頭（リード文）で読者の現状を代弁し、「私のことが書かれている」と思わせる\"\n    },\n    {\n      \"type\": \"emotion\",\n      \"content\": \"「機能表の『○』の数だけで選んで、本当に大丈夫だろうか？」という、スペック比較だけでは拭えない漠然とした不安を言語化する。\",\n      \"placement_suggestion\": \"比較表の直前または直後（決定回避の法則への対策）\"\n    },\n    {\n      \"type\": \"empathy\",\n      \"content\": \"「eラーニングの導入は、ゴールではなく『孤独な戦い』の始まりになりがちです。だからこそ、並走してくれるサポート体制が命綱になります。」と、担当者のプレッシャーを肯定し、寄り添う。\",\n      \"placement_suggestion\": \"サポート体制や定着支援機能の解説セクション\"\n    }\n  ],\n  \"experience_episodes\": [\n    {\n      \"scenario\": \"Excel管理の限界とヒヤリハット\",\n      \"narrative\": \"「受講状況を管理するExcelファイル、誰かがフィルタをかけたまま保存してしまい、集計がズレていたことに会議直前で気づいた冷や汗…。もう、手作業での管理は限界だと感じた瞬間でした。」\",\n      \"lesson\": \"LMS導入は「楽をするため」ではなく、「正確で安全なデータ管理」のために必須の投資である（自分への言い訳・正当化）。\"\n    },\n    {\n      \"scenario\": \"過去の失敗（または他社の失敗談）\",\n      \"narrative\": \"「『多機能で安いから』と決めた以前のツール。マニュアルを見ないとどこに何があるかわからない複雑な画面で、結局社員からの『使い方がわからない』という問い合わせ対応に追われ、半年で誰もログインしなくなりました。」\",\n      \"lesson\": \"機能の豊富さよりも、マニュアルなしで直感的に使える「UI/UX（使いやすさ）」こそが、定着の最大の鍵である。\"\n    }\n  ],\n  \"emotional_hooks\": [\n    \"「ジムの会員になっても行かなければ意味がないように、eラーニングも『ログインされなければ』ただのコストです。」\",\n    \"「研修担当者を『雑務係』から『組織を変える戦略家』へ。eラーニング導入は、あなたのキャリアを変える転機になります。」\",\n    \"「上司を説得するための『費用対効果』の算出、一人で悩んでいませんか？稟議書の書き方までサポートする視点で選びましょう。」\"\n  ]\n}\n```",
  "parsed_data": {
    "emotional_analysis": {
      "primary_emotion": "導入失敗への不安（損失回避）",
      "secondary_emotions": [
        "業務過多による疲弊感（現状からの脱却願望）",
        "経営層と現場の板挟みによる孤独感",
        "正しい選択をして評価されたいという承認欲求"
      ],
      "pain_points": [
        "高額なシステムを導入しても、結局社員が使わず『デジタル廃墟』化してしまうことへの恐怖",
        "「DX推進」と丸投げされたが、IT専門知識に自信がなく、ベンダーの専門用語に圧倒されている",
        "Excelでの受講管理や会場手配など、付加価値の低い事務作業に忙殺され、本来の人材育成業務に手が回らない"
      ],
      "desires": [
        "「システムを入れた」だけでなく、「社員が自発的に学び始めた」という成果を経営層に報告したい",
        "煩雑な事務作業から解放され、定時で帰れるような効率的な運用体制を作りたい",
        "何かあった時にすぐに相談できる、システムベンダー以上の「パートナー」が欲しい"
      ]
    },
    "human_touch_patterns": [
      {
        "type": "experience",
        "content": "「研修の前日は、会場設営と資料印刷で残業が確定する」「終わった後は、未提出者の督促メールとExcelへの転記作業が待っている」という、泥臭い現場のリアルな描写。",
        "placement_suggestion": "記事冒頭（リード文）で読者の現状を代弁し、「私のことが書かれている」と思わせる"
      },
      {
        "type": "emotion",
        "content": "「機能表の『○』の数だけで選んで、本当に大丈夫だろうか？」という、スペック比較だけでは拭えない漠然とした不安を言語化する。",
        "placement_suggestion": "比較表の直前または直後（決定回避の法則への対策）"
      },
      {
        "type": "empathy",
        "content": "「eラーニングの導入は、ゴールではなく『孤独な戦い』の始まりになりがちです。だからこそ、並走してくれるサポート体制が命綱になります。」と、担当者のプレッシャーを肯定し、寄り添う。",
        "placement_suggestion": "サポート体制や定着支援機能の解説セクション"
      }
    ],
    "experience_episodes": [
      {
        "scenario": "Excel管理の限界とヒヤリハット",
        "narrative": "「受講状況を管理するExcelファイル、誰かがフィルタをかけたまま保存してしまい、集計がズレていたことに会議直前で気づいた冷や汗…。もう、手作業での管理は限界だと感じた瞬間でした。」",
        "lesson": "LMS導入は「楽をするため」ではなく、「正確で安全なデータ管理」のために必須の投資である（自分への言い訳・正当化）。"
      },
      {
        "scenario": "過去の失敗（または他社の失敗談）",
        "narrative": "「『多機能で安いから』と決めた以前のツール。マニュアルを見ないとどこに何があるかわからない複雑な画面で、結局社員からの『使い方がわからない』という問い合わせ対応に追われ、半年で誰もログインしなくなりました。」",
        "lesson": "機能の豊富さよりも、マニュアルなしで直感的に使える「UI/UX（使いやすさ）」こそが、定着の最大の鍵である。"
      }
    ],
    "emotional_hooks": [
      "「ジムの会員になっても行かなければ意味がないように、eラーニングも『ログインされなければ』ただのコストです。」",
      "「研修担当者を『雑務係』から『組織を変える戦略家』へ。eラーニング導入は、あなたのキャリアを変える転機になります。」",
      "「上司を説得するための『費用対効果』の算出、一人で悩んでいませんか？稟議書の書き方までサポートする視点で選びましょう。」"
    ]
  },
  "metadata": {
    "generated_at": "2026-01-14T06:30:06.222243",
    "model": "gemini-3-pro-preview",
    "model_config": {
      "platform": "gemini",
      "model": "gemini-3-pro-preview"
    },
    "input_files": [
      "step0",
      "step1",
      "step3a",
      "step3b",
      "step3c",
      "step1_5"
    ]
  },
  "quality": {
    "attempts": 1,
    "issues": []
  },
  "token_usage": {
    "input": 17486,
    "output": 1042
  },
  "output_path": "storage/dev-tenant-001/3bf5c695-4c4c-4cad-ae18-7534dbd367a8/step3_5/output.json",
  "output_digest": "5a95a3a42e5b998d"
}