{
  "step": "step3_5",
  "keyword": "eラーニング 企業",
  "emotional_analysis": {
    "primary_emotion": "失敗への恐怖（損失回避）",
    "secondary_emotions": [
      "現状のExcel管理業務に対する疲弊感",
      "経営層からのDX圧力に対する焦燥感",
      "社員に受け入れられるかどうかの不安",
      "業務効率化による解放感への期待"
    ],
    "pain_points": [
      "「高機能なシステムを入れたが誰も使わない」という事態になり、社内での信用を失うこと",
      "金曜日の夕方に、終わりの見えない受講履歴のExcel集計作業に追われること",
      "地方拠点の社員から「研修の機会が不公平だ」という不満の声が上がること"
    ],
    "desires": [
      "「このシステムのおかげで研修が楽になった」と現場社員から感謝されたい",
      "集計業務を自動化し、本来注力すべき「人材育成戦略」の立案に時間を使いたい",
      "経営会議で「コストを〇〇%削減しつつ、受講率は向上した」と胸を張って報告したい"
    ]
  },
  "human_touch_patterns": [
    {
      "type": "experience",
      "content": "「またあのExcelとの格闘が始まるのか…」期末の研修報告シーズン、何百行ものデータとにらめっこしながら、ため息をついた経験はありませんか？",
      "placement_suggestion": "記事冒頭（導入部）の課題共感パート"
    },
    {
      "type": "emotion",
      "content": "正直なところ、eラーニングシステムのカタログを見ても「機能が多すぎて何が違うのか分からない」と途方に暮れてしまうのは、あなただけではありません。",
      "placement_suggestion": "比較・選定の難しさを語るセクション（問題提起の後）"
    },
    {
      "type": "empathy",
      "content": "システム選びで最も怖いのは、決済者の承認を得て導入した後に「使いにくい」と社員にそっぽを向かれることですよね。私たちはその「責任の重さ」を理解しています。",
      "placement_suggestion": "失敗しない選び方やサポート体制を紹介する直前"
    }
  ],
  "experience_episodes": [
    {
      "scenario": "多機能すぎるシステムを選んでしまった失敗談",
      "narrative": "「大は小を兼ねる」と思い、最も機能が豊富なシステムを導入しました。しかし、管理画面が複雑すぎて人事担当者ですら使いこなせず、社員からは「ログイン方法が分からない」という問い合わせが殺到。結局、1年で解約することになりました。",
      "lesson": "選ぶべきは「最高機能」ではなく、自社のITリテラシーに合った「最適機能」である。"
    },
    {
      "scenario": "Excel管理からの脱却による成功体験",
      "narrative": "以前は、未受講者一人ひとりにリマインドメールを手動で送っていました。システム導入後は、自動通知機能が勝手に背中を押してくれます。「催促する」という精神的ストレスから解放された時、初めてDXの恩恵を実感しました。",
      "lesson": "システムの価値は機能リストではなく、「担当者の精神的負担の軽減」にある。"
    },
    {
      "scenario": "地方拠点との教育格差の解消",
      "narrative": "「東京の本社ばかり研修が充実していてズルい」。地方営業所の若手から言われた一言が胸に刺さっていました。オンライン化によって、沖縄の社員も北海道の社員も、同じ質の教育を好きな時間に受けられるようになった時、組織の一体感が増したのを感じました。",
      "lesson": "eラーニングは単なるツールではなく、組織の「公平性」を担保するインフラになる。"
    }
  ],
  "emotional_hooks": [
    "一番高いシステムとは、初期費用が高いものではなく、「導入したのに誰も使わないシステム」のことです。",
    "あなたの仕事は「研修の出欠確認」ではありません。「社員の成長を支援すること」はずです。事務作業はシステムに任せましょう。",
    "「失敗しない」ための第一歩は、カタログを集めることではなく、自社の社員の顔を思い浮かべることから始まります。"
  ],
  "phase_emotional_map": {
    "phase1": {
      "dominant_emotion": "",
      "empathy_statements": [],
      "experience_episodes": []
    },
    "phase2": {
      "dominant_emotion": "",
      "empathy_statements": [],
      "experience_episodes": []
    },
    "phase3": {
      "dominant_emotion": "",
      "empathy_statements": [],
      "experience_episodes": []
    }
  },
  "behavioral_economics_hooks": {
    "loss_aversion_hook": "",
    "social_proof_hook": "",
    "authority_hook": "",
    "scarcity_hook": ""
  },
  "placement_instructions": [],
  "raw_output": "ご提示いただいた詳細なペルソナ、競合分析、行動経済学的洞察に基づき、読者（40代人事・総務課長）の「失敗への不安」に寄り添いつつ、「現状打破への希望」を醸成する人間味あふれる要素を作成しました。\n\n```json\n{\n  \"emotional_analysis\": {\n    \"primary_emotion\": \"失敗への恐怖（損失回避）\",\n    \"secondary_emotions\": [\n      \"現状のExcel管理業務に対する疲弊感\",\n      \"経営層からのDX圧力に対する焦燥感\",\n      \"社員に受け入れられるかどうかの不安\",\n      \"業務効率化による解放感への期待\"\n    ],\n    \"pain_points\": [\n      \"「高機能なシステムを入れたが誰も使わない」という事態になり、社内での信用を失うこと\",\n      \"金曜日の夕方に、終わりの見えない受講履歴のExcel集計作業に追われること\",\n      \"地方拠点の社員から「研修の機会が不公平だ」という不満の声が上がること\"\n    ],\n    \"desires\": [\n      \"「このシステムのおかげで研修が楽になった」と現場社員から感謝されたい\",\n      \"集計業務を自動化し、本来注力すべき「人材育成戦略」の立案に時間を使いたい\",\n      \"経営会議で「コストを〇〇%削減しつつ、受講率は向上した」と胸を張って報告したい\"\n    ]\n  },\n  \"human_touch_patterns\": [\n    {\n      \"type\": \"experience\",\n      \"content\": \"「またあのExcelとの格闘が始まるのか…」期末の研修報告シーズン、何百行ものデータとにらめっこしながら、ため息をついた経験はありませんか？\",\n      \"placement_suggestion\": \"記事冒頭（導入部）の課題共感パート\"\n    },\n    {\n      \"type\": \"emotion\",\n      \"content\": \"正直なところ、eラーニングシステムのカタログを見ても「機能が多すぎて何が違うのか分からない」と途方に暮れてしまうのは、あなただけではありません。\",\n      \"placement_suggestion\": \"比較・選定の難しさを語るセクション（問題提起の後）\"\n    },\n    {\n      \"type\": \"empathy\",\n      \"content\": \"システム選びで最も怖いのは、決済者の承認を得て導入した後に「使いにくい」と社員にそっぽを向かれることですよね。私たちはその「責任の重さ」を理解しています。\",\n      \"placement_suggestion\": \"失敗しない選び方やサポート体制を紹介する直前\"\n    }\n  ],\n  \"experience_episodes\": [\n    {\n      \"scenario\": \"多機能すぎるシステムを選んでしまった失敗談\",\n      \"narrative\": \"「大は小を兼ねる」と思い、最も機能が豊富なシステムを導入しました。しかし、管理画面が複雑すぎて人事担当者ですら使いこなせず、社員からは「ログイン方法が分からない」という問い合わせが殺到。結局、1年で解約することになりました。\",\n      \"lesson\": \"選ぶべきは「最高機能」ではなく、自社のITリテラシーに合った「最適機能」である。\"\n    },\n    {\n      \"scenario\": \"Excel管理からの脱却による成功体験\",\n      \"narrative\": \"以前は、未受講者一人ひとりにリマインドメールを手動で送っていました。システム導入後は、自動通知機能が勝手に背中を押してくれます。「催促する」という精神的ストレスから解放された時、初めてDXの恩恵を実感しました。\",\n      \"lesson\": \"システムの価値は機能リストではなく、「担当者の精神的負担の軽減」にある。\"\n    },\n    {\n      \"scenario\": \"地方拠点との教育格差の解消\",\n      \"narrative\": \"「東京の本社ばかり研修が充実していてズルい」。地方営業所の若手から言われた一言が胸に刺さっていました。オンライン化によって、沖縄の社員も北海道の社員も、同じ質の教育を好きな時間に受けられるようになった時、組織の一体感が増したのを感じました。\",\n      \"lesson\": \"eラーニングは単なるツールではなく、組織の「公平性」を担保するインフラになる。\"\n    }\n  ],\n  \"emotional_hooks\": [\n    \"一番高いシステムとは、初期費用が高いものではなく、「導入したのに誰も使わないシステム」のことです。\",\n    \"あなたの仕事は「研修の出欠確認」ではありません。「社員の成長を支援すること」はずです。事務作業はシステムに任せましょう。\",\n    \"「失敗しない」ための第一歩は、カタログを集めることではなく、自社の社員の顔を思い浮かべることから始まります。\"\n  ]\n}\n```",
  "parsed_data": {
    "emotional_analysis": {
      "primary_emotion": "失敗への恐怖（損失回避）",
      "secondary_emotions": [
        "現状のExcel管理業務に対する疲弊感",
        "経営層からのDX圧力に対する焦燥感",
        "社員に受け入れられるかどうかの不安",
        "業務効率化による解放感への期待"
      ],
      "pain_points": [
        "「高機能なシステムを入れたが誰も使わない」という事態になり、社内での信用を失うこと",
        "金曜日の夕方に、終わりの見えない受講履歴のExcel集計作業に追われること",
        "地方拠点の社員から「研修の機会が不公平だ」という不満の声が上がること"
      ],
      "desires": [
        "「このシステムのおかげで研修が楽になった」と現場社員から感謝されたい",
        "集計業務を自動化し、本来注力すべき「人材育成戦略」の立案に時間を使いたい",
        "経営会議で「コストを〇〇%削減しつつ、受講率は向上した」と胸を張って報告したい"
      ]
    },
    "human_touch_patterns": [
      {
        "type": "experience",
        "content": "「またあのExcelとの格闘が始まるのか…」期末の研修報告シーズン、何百行ものデータとにらめっこしながら、ため息をついた経験はありませんか？",
        "placement_suggestion": "記事冒頭（導入部）の課題共感パート"
      },
      {
        "type": "emotion",
        "content": "正直なところ、eラーニングシステムのカタログを見ても「機能が多すぎて何が違うのか分からない」と途方に暮れてしまうのは、あなただけではありません。",
        "placement_suggestion": "比較・選定の難しさを語るセクション（問題提起の後）"
      },
      {
        "type": "empathy",
        "content": "システム選びで最も怖いのは、決済者の承認を得て導入した後に「使いにくい」と社員にそっぽを向かれることですよね。私たちはその「責任の重さ」を理解しています。",
        "placement_suggestion": "失敗しない選び方やサポート体制を紹介する直前"
      }
    ],
    "experience_episodes": [
      {
        "scenario": "多機能すぎるシステムを選んでしまった失敗談",
        "narrative": "「大は小を兼ねる」と思い、最も機能が豊富なシステムを導入しました。しかし、管理画面が複雑すぎて人事担当者ですら使いこなせず、社員からは「ログイン方法が分からない」という問い合わせが殺到。結局、1年で解約することになりました。",
        "lesson": "選ぶべきは「最高機能」ではなく、自社のITリテラシーに合った「最適機能」である。"
      },
      {
        "scenario": "Excel管理からの脱却による成功体験",
        "narrative": "以前は、未受講者一人ひとりにリマインドメールを手動で送っていました。システム導入後は、自動通知機能が勝手に背中を押してくれます。「催促する」という精神的ストレスから解放された時、初めてDXの恩恵を実感しました。",
        "lesson": "システムの価値は機能リストではなく、「担当者の精神的負担の軽減」にある。"
      },
      {
        "scenario": "地方拠点との教育格差の解消",
        "narrative": "「東京の本社ばかり研修が充実していてズルい」。地方営業所の若手から言われた一言が胸に刺さっていました。オンライン化によって、沖縄の社員も北海道の社員も、同じ質の教育を好きな時間に受けられるようになった時、組織の一体感が増したのを感じました。",
        "lesson": "eラーニングは単なるツールではなく、組織の「公平性」を担保するインフラになる。"
      }
    ],
    "emotional_hooks": [
      "一番高いシステムとは、初期費用が高いものではなく、「導入したのに誰も使わないシステム」のことです。",
      "あなたの仕事は「研修の出欠確認」ではありません。「社員の成長を支援すること」はずです。事務作業はシステムに任せましょう。",
      "「失敗しない」ための第一歩は、カタログを集めることではなく、自社の社員の顔を思い浮かべることから始まります。"
    ]
  },
  "metadata": {
    "generated_at": "2026-01-19T07:25:58.092368",
    "model": "gemini-3-pro-preview",
    "model_config": {
      "platform": "gemini",
      "model": "gemini-3-pro-preview"
    },
    "input_files": [
      "step0",
      "step1",
      "step3a",
      "step3b",
      "step3c",
      "step1_5"
    ]
  },
  "quality": {
    "attempts": 1,
    "issues": []
  },
  "token_usage": {
    "input": 18992,
    "output": 1063
  },
  "output_path": "storage/dev-tenant-001/3c350a98-ba86-4853-b87a-5bbc3ba88770/step3_5/output.json",
  "output_digest": "67691c61ad1a490d"
}