{
  "step": "step3_5",
  "keyword": "eラーニング 企業",
  "emotional_analysis": {
    "primary_emotion": "失敗への不安（損失回避）",
    "secondary_emotions": [
      "アナログ業務からの解放願望（疲労感）",
      "社内の冷ややかな反応に対する孤独感",
      "時代に遅れることへの焦燥感（DX推進圧力）"
    ],
    "pain_points": [
      "「導入したのに誰も使わない」という事態になり、無駄な投資として責任を問われるのが怖い",
      "日々のExcelでの進捗管理や、未受講者への督促メール送信という不毛な作業に忙殺されている",
      "現場社員から「忙しいのにまた研修か」と煙たがられ、教育担当としてのやりがいを感じにくい"
    ],
    "desires": [
      "「このシステムのおかげで社員が育った」と経営層・現場双方から感謝されたい",
      "事務作業を自動化し、本来の業務である「人材育成の企画」や「社員との対話」に時間を使いたい",
      "自社の風土に合った、無理なく定着する仕組みを自信を持って選びたい"
    ]
  },
  "human_touch_patterns": [
    {
      "type": "experience",
      "content": "月末になるとExcelの受講管理表とにらめっこし、終わっていない社員一人ひとりに「催促メール」を送る...。送信ボタンを押すたびに、「また口うるさい人事だと思われているんだろうな」と心が少し重くなる瞬間。",
      "placement_suggestion": "記事冒頭（導入部）の共感形成パート"
    },
    {
      "type": "emotion",
      "content": "数あるサービス比較表を見れば見るほど、「機能はすごいけれど、本当にうちの社員が使いこなせるのだろうか？」という不安が募りませんか？高機能なツールが欲しいわけではなく、社員が「これならやれる」と思ってくれる環境が欲しいだけなのに。",
      "placement_suggestion": "機能比較・選定基準の解説セクション直前"
    },
    {
      "type": "empathy",
      "content": "これまでアナログな環境で、社員の成長のために奔走されてきたこと、本当に頭が下がります。システム導入は「手抜き」ではありません。あなたが本来注力すべき「人に向き合う時間」を取り戻すための、頼れるパートナー探しなのです。",
      "placement_suggestion": "解決策（おすすめサービス紹介）の提示直前"
    }
  ],
  "experience_episodes": [
    {
      "scenario": "集合研修の準備と事後処理",
      "narrative": "会議室の確保、プロジェクターの準備、配布資料の印刷...。研修当日は運営に走り回り、終わればアンケートの集計手入力。ふと「私は教育担当なのか、イベント運営担当なのか」と自問自答してしまった経験はありませんか？",
      "lesson": "「運営」に使うエネルギーを「教育の中身」に注ぐために、テクノロジーを頼りましょう。"
    },
    {
      "scenario": "高機能すぎるシステム導入の落とし穴",
      "narrative": "「大は小を兼ねる」と多機能なシステムを導入したA社。しかし、管理画面が複雑すぎて人事担当者すら使いこなせず、現場社員からは「ログイン方法がわからない」と問い合わせの嵐。結局、半年後には誰も開かない「デジタル廃墟」になってしまいました。",
      "lesson": "「何ができるか（機能）」よりも「迷わず使えるか（体験）」が、定着の最大の鍵です。"
    }
  ],
  "emotional_hooks": [
    "「導入して終わり」にしたくない。社員の「やらされ感」を「やってよかった」に変えるeラーニング選び。",
    "もう、Excelでの進捗管理に追われて「本来やりたかった教育」を後回しにするのは終わりにしませんか？",
    "失敗しない選び方の極意は、機能一覧表の「○の数」ではなく、運用担当者の「笑顔の数」にありました。"
  ],
  "phase_emotional_map": {
    "phase1": {
      "dominant_emotion": "",
      "empathy_statements": [],
      "experience_episodes": []
    },
    "phase2": {
      "dominant_emotion": "",
      "empathy_statements": [],
      "experience_episodes": []
    },
    "phase3": {
      "dominant_emotion": "",
      "empathy_statements": [],
      "experience_episodes": []
    }
  },
  "behavioral_economics_hooks": {
    "loss_aversion_hook": "",
    "social_proof_hook": "",
    "authority_hook": "",
    "scarcity_hook": ""
  },
  "placement_instructions": [],
  "raw_output": "ご提示いただいた詳細な分析データに基づき、従業員100〜500名規模の中堅・中小企業の人事担当者（30代後半〜40代）の心に深く刺さる「人間味」のある要素を生成しました。\n\n```json\n{\n  \"emotional_analysis\": {\n    \"primary_emotion\": \"失敗への不安（損失回避）\",\n    \"secondary_emotions\": [\n      \"アナログ業務からの解放願望（疲労感）\",\n      \"社内の冷ややかな反応に対する孤独感\",\n      \"時代に遅れることへの焦燥感（DX推進圧力）\"\n    ],\n    \"pain_points\": [\n      \"「導入したのに誰も使わない」という事態になり、無駄な投資として責任を問われるのが怖い\",\n      \"日々のExcelでの進捗管理や、未受講者への督促メール送信という不毛な作業に忙殺されている\",\n      \"現場社員から「忙しいのにまた研修か」と煙たがられ、教育担当としてのやりがいを感じにくい\"\n    ],\n    \"desires\": [\n      \"「このシステムのおかげで社員が育った」と経営層・現場双方から感謝されたい\",\n      \"事務作業を自動化し、本来の業務である「人材育成の企画」や「社員との対話」に時間を使いたい\",\n      \"自社の風土に合った、無理なく定着する仕組みを自信を持って選びたい\"\n    ]\n  },\n  \"human_touch_patterns\": [\n    {\n      \"type\": \"experience\",\n      \"content\": \"月末になるとExcelの受講管理表とにらめっこし、終わっていない社員一人ひとりに「催促メール」を送る...。送信ボタンを押すたびに、「また口うるさい人事だと思われているんだろうな」と心が少し重くなる瞬間。\",\n      \"placement_suggestion\": \"記事冒頭（導入部）の共感形成パート\"\n    },\n    {\n      \"type\": \"emotion\",\n      \"content\": \"数あるサービス比較表を見れば見るほど、「機能はすごいけれど、本当にうちの社員が使いこなせるのだろうか？」という不安が募りませんか？高機能なツールが欲しいわけではなく、社員が「これならやれる」と思ってくれる環境が欲しいだけなのに。\",\n      \"placement_suggestion\": \"機能比較・選定基準の解説セクション直前\"\n    },\n    {\n      \"type\": \"empathy\",\n      \"content\": \"これまでアナログな環境で、社員の成長のために奔走されてきたこと、本当に頭が下がります。システム導入は「手抜き」ではありません。あなたが本来注力すべき「人に向き合う時間」を取り戻すための、頼れるパートナー探しなのです。\",\n      \"placement_suggestion\": \"解決策（おすすめサービス紹介）の提示直前\"\n    }\n  ],\n  \"experience_episodes\": [\n    {\n      \"scenario\": \"集合研修の準備と事後処理\",\n      \"narrative\": \"会議室の確保、プロジェクターの準備、配布資料の印刷...。研修当日は運営に走り回り、終わればアンケートの集計手入力。ふと「私は教育担当なのか、イベント運営担当なのか」と自問自答してしまった経験はありませんか？\",\n      \"lesson\": \"「運営」に使うエネルギーを「教育の中身」に注ぐために、テクノロジーを頼りましょう。\"\n    },\n    {\n      \"scenario\": \"高機能すぎるシステム導入の落とし穴\",\n      \"narrative\": \"「大は小を兼ねる」と多機能なシステムを導入したA社。しかし、管理画面が複雑すぎて人事担当者すら使いこなせず、現場社員からは「ログイン方法がわからない」と問い合わせの嵐。結局、半年後には誰も開かない「デジタル廃墟」になってしまいました。\",\n      \"lesson\": \"「何ができるか（機能）」よりも「迷わず使えるか（体験）」が、定着の最大の鍵です。\"\n    }\n  ],\n  \"emotional_hooks\": [\n    \"「導入して終わり」にしたくない。社員の「やらされ感」を「やってよかった」に変えるeラーニング選び。\",\n    \"もう、Excelでの進捗管理に追われて「本来やりたかった教育」を後回しにするのは終わりにしませんか？\",\n    \"失敗しない選び方の極意は、機能一覧表の「○の数」ではなく、運用担当者の「笑顔の数」にありました。\"\n  ]\n}\n```",
  "parsed_data": {
    "emotional_analysis": {
      "primary_emotion": "失敗への不安（損失回避）",
      "secondary_emotions": [
        "アナログ業務からの解放願望（疲労感）",
        "社内の冷ややかな反応に対する孤独感",
        "時代に遅れることへの焦燥感（DX推進圧力）"
      ],
      "pain_points": [
        "「導入したのに誰も使わない」という事態になり、無駄な投資として責任を問われるのが怖い",
        "日々のExcelでの進捗管理や、未受講者への督促メール送信という不毛な作業に忙殺されている",
        "現場社員から「忙しいのにまた研修か」と煙たがられ、教育担当としてのやりがいを感じにくい"
      ],
      "desires": [
        "「このシステムのおかげで社員が育った」と経営層・現場双方から感謝されたい",
        "事務作業を自動化し、本来の業務である「人材育成の企画」や「社員との対話」に時間を使いたい",
        "自社の風土に合った、無理なく定着する仕組みを自信を持って選びたい"
      ]
    },
    "human_touch_patterns": [
      {
        "type": "experience",
        "content": "月末になるとExcelの受講管理表とにらめっこし、終わっていない社員一人ひとりに「催促メール」を送る...。送信ボタンを押すたびに、「また口うるさい人事だと思われているんだろうな」と心が少し重くなる瞬間。",
        "placement_suggestion": "記事冒頭（導入部）の共感形成パート"
      },
      {
        "type": "emotion",
        "content": "数あるサービス比較表を見れば見るほど、「機能はすごいけれど、本当にうちの社員が使いこなせるのだろうか？」という不安が募りませんか？高機能なツールが欲しいわけではなく、社員が「これならやれる」と思ってくれる環境が欲しいだけなのに。",
        "placement_suggestion": "機能比較・選定基準の解説セクション直前"
      },
      {
        "type": "empathy",
        "content": "これまでアナログな環境で、社員の成長のために奔走されてきたこと、本当に頭が下がります。システム導入は「手抜き」ではありません。あなたが本来注力すべき「人に向き合う時間」を取り戻すための、頼れるパートナー探しなのです。",
        "placement_suggestion": "解決策（おすすめサービス紹介）の提示直前"
      }
    ],
    "experience_episodes": [
      {
        "scenario": "集合研修の準備と事後処理",
        "narrative": "会議室の確保、プロジェクターの準備、配布資料の印刷...。研修当日は運営に走り回り、終わればアンケートの集計手入力。ふと「私は教育担当なのか、イベント運営担当なのか」と自問自答してしまった経験はありませんか？",
        "lesson": "「運営」に使うエネルギーを「教育の中身」に注ぐために、テクノロジーを頼りましょう。"
      },
      {
        "scenario": "高機能すぎるシステム導入の落とし穴",
        "narrative": "「大は小を兼ねる」と多機能なシステムを導入したA社。しかし、管理画面が複雑すぎて人事担当者すら使いこなせず、現場社員からは「ログイン方法がわからない」と問い合わせの嵐。結局、半年後には誰も開かない「デジタル廃墟」になってしまいました。",
        "lesson": "「何ができるか（機能）」よりも「迷わず使えるか（体験）」が、定着の最大の鍵です。"
      }
    ],
    "emotional_hooks": [
      "「導入して終わり」にしたくない。社員の「やらされ感」を「やってよかった」に変えるeラーニング選び。",
      "もう、Excelでの進捗管理に追われて「本来やりたかった教育」を後回しにするのは終わりにしませんか？",
      "失敗しない選び方の極意は、機能一覧表の「○の数」ではなく、運用担当者の「笑顔の数」にありました。"
    ]
  },
  "metadata": {
    "generated_at": "2026-01-16T11:23:33.424818",
    "model": "gemini-3-pro-preview",
    "model_config": {
      "platform": "gemini",
      "model": "gemini-3-pro-preview"
    },
    "input_files": [
      "step0",
      "step1",
      "step3a",
      "step3b",
      "step3c",
      "step1_5"
    ]
  },
  "quality": {
    "attempts": 1,
    "issues": []
  },
  "token_usage": {
    "input": 19293,
    "output": 1002
  },
  "output_path": "storage/dev-tenant-001/48b17938-48a5-45ff-af7a-88a163cb85d4/step3_5/output.json",
  "output_digest": "2cff574f6b5b074b"
}